fjrpc/.gitignore
fjrpc/__init__.py
fjrpc/jsonrpc.py
fjrpc/method.py
fjrpc/request.py
fjrpc/response.py
fjrpc/status.py
fjrpc-0.0.1.dist-info/METADATA
fjrpc-0.0.1.dist-info/WHEEL
fjrpc-0.0.1.dist-info/licenses/LICENSE
fjrpc-0.0.1.dist-info/RECORD
