Metadata-Version: 2.1
Name: fjrpc
Version: 0.0.1
Summary: jsonrpc with fastapi
Author-email: Latrevious <kerwin2509456238@gmail.com>
License-File: LICENSE
Classifier: License :: OSI Approved :: MIT License
Classifier: Operating System :: OS Independent
Classifier: Programming Language :: Python :: 3
Requires-Python: >=3.7
Requires-Dist: fastapi
